example/yaprak_example.py
src/yaprak/__init__.py
src/yaprak/yaprak.py
yaprak_delete-0.1.2.dist-info/METADATA
yaprak_delete-0.1.2.dist-info/WHEEL
yaprak_delete-0.1.2.dist-info/licenses/LICENSE
yaprak_delete-0.1.2.dist-info/RECORD
