Metadata-Version: 2.1
Name: yaprak-delete
Version: 0.1.2
Summary: A small package for processing and analyzing data in batches.
Project-URL: Homepage, https://github.com/arta-ns/yaprak
Project-URL: Bug Tracker, https://github.com/arta-ns/yaprak/issues
Project-URL: Documentation, https://github.com/arta-ns/yaprak/tree/main/src/yaprak/html/yaprak/index.html
Author-email: "N. Sertac Artan" <artans.github@gmail.com>
License-File: LICENSE
Classifier: License :: OSI Approved :: MIT License
Classifier: Operating System :: OS Independent
Classifier: Programming Language :: Python :: 3
Requires-Python: >=3.7
